codechest/__init__.py
codechest/main.py
codechest-0.1.0.dist-info/METADATA
codechest-0.1.0.dist-info/WHEEL
codechest-0.1.0.dist-info/top_level.txt
codechest-0.1.0.dist-info/RECORD
