Metadata-Version: 2.4
Name: codechest
Version: 0.1.0
Summary: CodeChest - test paketi
Requires-Python: >=3.8
Dynamic: description-content-type
Dynamic: requires-python
Dynamic: summary
